fmDataAPI/__init__.py
fmDataAPI/fmDataAPI.py
fmrest/__init__.py
fmrest/dataAPI/__init__.py
fmrest/dataAPI/fmDataAPI.py
fmrest-1.1.2.dist-info/LICENSE.txt
fmrest-1.1.2.dist-info/METADATA
fmrest-1.1.2.dist-info/RECORD
fmrest-1.1.2.dist-info/WHEEL
fmrest-1.1.2.dist-info/top_level.txt
